old_norse_dictionary/__init__.py
old_norse_dictionary/dictionary.py
old_norse_dictionary/reader.py
old_norse_dictionary/resources/__init__.py
old_norse_dictionary/resources/default.json
old_norse_dictionary/resources/no-markup.json
old_norse_dictionary-1.0.0.dist-info/LICENSE
old_norse_dictionary-1.0.0.dist-info/METADATA
old_norse_dictionary-1.0.0.dist-info/WHEEL
old_norse_dictionary-1.0.0.dist-info/top_level.txt
old_norse_dictionary-1.0.0.dist-info/RECORD
