Metadata-Version: 2.1
Name: old-norse-dictionary
Version: 1.0.0
Summary: Old Norse Dictionary for Python. From The Cleasby & Vigfusson Old Norse to English Dictionary.
Home-page: https://github.com/stscoundrel/old-norse-dictionary-py
Author: stscoundrel
License: UNKNOWN
Platform: UNKNOWN
Requires-Python: >=3.9
License-File: LICENSE
